mergemate/__init__.py
mergemate/llmware/__init__.py
mergemate/llmware/reviewer_agent.py
mergemate/prompts/__init__.py
mergemate/prompts/answer_comment.py
mergemate/prompts/create_review.py
mergemate/prompts/explain_code.py
mergemate/providers/__init__.py
mergemate/providers/github.py
mergemate/scripts/__init__.py
mergemate/scripts/github/__init__.py
mergemate/scripts/github/comment_handler.py
mergemate/scripts/github/pr_review.py
mergemate-0.1.5.data/scripts/comment_handler.py
mergemate-0.1.5.dist-info/LICENSE
mergemate-0.1.5.dist-info/METADATA
mergemate-0.1.5.dist-info/WHEEL
mergemate-0.1.5.dist-info/top_level.txt
mergemate-0.1.5.dist-info/RECORD
