Metadata-Version: 2.1
Name: mergemate
Version: 0.1.5
Summary: An automated tool to handle GitHub pull requests and comments.
Home-page: http://pypi.python.org/pypi/MergeMate/
Author: Hardeep Singh
Author-email: hardeep0khalsa122@gmail.com
License: LICENSE.txt
Requires-Python: >=3.9
License-File: LICENSE
Requires-Dist: llmware
Requires-Dist: pygithub
